pyreveal/__init__.py
pyreveal/background.py
pyreveal/core.py
pyreveal/exceptions.py
pyreveal/helpers.py
pyreveal/revealjs/.git
pyreveal/revealjs/.github/CONTRIBUTING.md
pyreveal/revealjs/.github/FUNDING.yml
pyreveal/revealjs/.github/workflows/js.yml
pyreveal/revealjs/.gitignore
pyreveal/revealjs/.npmignore
pyreveal/revealjs/LICENSE
pyreveal/revealjs/README.md
pyreveal/revealjs/css/layout.scss
pyreveal/revealjs/css/print/paper.scss
pyreveal/revealjs/css/print/pdf.scss
pyreveal/revealjs/css/reveal.scss
pyreveal/revealjs/css/theme/README.md
pyreveal/revealjs/css/theme/source/beige.scss
pyreveal/revealjs/css/theme/source/black-contrast.scss
pyreveal/revealjs/css/theme/source/black.scss
pyreveal/revealjs/css/theme/source/blood.scss
pyreveal/revealjs/css/theme/source/dracula.scss
pyreveal/revealjs/css/theme/source/league.scss
pyreveal/revealjs/css/theme/source/moon.scss
pyreveal/revealjs/css/theme/source/night.scss
pyreveal/revealjs/css/theme/source/serif.scss
pyreveal/revealjs/css/theme/source/simple.scss
pyreveal/revealjs/css/theme/source/sky.scss
pyreveal/revealjs/css/theme/source/solarized.scss
pyreveal/revealjs/css/theme/source/white-contrast.scss
pyreveal/revealjs/css/theme/source/white.scss
pyreveal/revealjs/css/theme/template/exposer.scss
pyreveal/revealjs/css/theme/template/mixins.scss
pyreveal/revealjs/css/theme/template/settings.scss
pyreveal/revealjs/css/theme/template/theme.scss
pyreveal/revealjs/demo.html
pyreveal/revealjs/dist/reset.css
pyreveal/revealjs/dist/reveal.css
pyreveal/revealjs/dist/reveal.esm.js
pyreveal/revealjs/dist/reveal.esm.js.map
pyreveal/revealjs/dist/reveal.js
pyreveal/revealjs/dist/reveal.js.map
pyreveal/revealjs/dist/theme/beige.css
pyreveal/revealjs/dist/theme/black-contrast.css
pyreveal/revealjs/dist/theme/black.css
pyreveal/revealjs/dist/theme/blood.css
pyreveal/revealjs/dist/theme/dracula.css
pyreveal/revealjs/dist/theme/fonts/league-gothic/LICENSE
pyreveal/revealjs/dist/theme/fonts/league-gothic/league-gothic.css
pyreveal-0.2.0.dist-info/LICENSE
pyreveal-0.2.0.dist-info/WHEEL
pyreveal-0.2.0.dist-info/METADATA
pyreveal-0.2.0.dist-info/RECORD
