Metadata-Version: 2.1
Name: pyreveal
Version: 0.2.0
Summary: A Python library to simplify the creation of presentations using Reveal.js.
License: MIT
Author: Ali Tavallaie
Author-email: a.tavallaie@gmail.com
Requires-Python: >=3.10,<4.0
Classifier: License :: OSI Approved :: MIT License
Classifier: Programming Language :: Python :: 3
Classifier: Programming Language :: Python :: 3.10
